g3matcha.py
g3read.py
test_ci.py
g3read-1.0.1.dist-info/licenses/LICENSE
g3read-1.0.1.dist-info/METADATA
g3read-1.0.1.dist-info/WHEEL
g3read-1.0.1.dist-info/top_level.txt
g3read-1.0.1.dist-info/RECORD
