Metadata-Version: 2.4
Name: g3read
Version: 1.0.1
Summary: Read Gadget2/3 snapshots, large simulations and catalogues
Home-page: https://aragagnin.github.io
Author: Antonio Ragagnin
Author-email: antonio.ragagnin@inaf.it
License: GPLv3+
License-File: LICENSE
Dynamic: author
Dynamic: author-email
Dynamic: home-page
Dynamic: license
Dynamic: license-file
Dynamic: summary
